jenerationutils/__init__.py
jenerationutils/benchmarker/README.md
jenerationutils/benchmarker/__init__.py
jenerationutils/benchmarker/benchmarker.py
jenerationutils/data_connections/README.md
jenerationutils/data_connections/__init__.py
jenerationutils/data_connections/base_connector.py
jenerationutils/data_connections/csv_connector.py
jenerationutils/data_connections/registry.py
jenerationutils/examples/imagejenerator.py
jenerationutils/jenerationrecord/README.md
jenerationutils/jenerationrecord/__init__.py
jenerationutils/jenerationrecord/base_generation_record.py
jenerationutils/jenerationrecord/csv_generation_record.py
jenerationutils/jenerationrecord/registry.py
jenerationutils-0.1.1.dist-info/METADATA
jenerationutils-0.1.1.dist-info/WHEEL
jenerationutils-0.1.1.dist-info/licenses/LICENSE
jenerationutils-0.1.1.dist-info/RECORD
