Metadata-Version: 2.4
Name: jenerationutils
Version: 0.1.1
Summary: Utils for GenAI workflows
License: MIT
License-File: LICENSE
Author: Warren Davies
Requires-Python: >=3.10
Classifier: Programming Language :: Python :: 3
Classifier: Programming Language :: Python :: 3.10
Classifier: License :: OSI Approved :: MIT License
Classifier: Operating System :: OS Independent
Classifier: Topic :: Scientific/Engineering :: Artificial Intelligence
Requires-Dist: pydantic (>=2.12.5,<3.0.0)
